ansimarkup/__init__.py
ansimarkup/__main__.py
ansimarkup/ansi.py
ansimarkup/logformatter.py
ansimarkup/markup.py
ansimarkup/tags.py
ansimarkup-2.1.0.dist-info/LICENSE.txt
ansimarkup-2.1.0.dist-info/METADATA
ansimarkup-2.1.0.dist-info/WHEEL
ansimarkup-2.1.0.dist-info/top_level.txt
ansimarkup-2.1.0.dist-info/RECORD
