Metadata-Version: 2.1
Name: ansimarkup
Version: 2.1.0
Summary: Produce colored terminal text with an xml-like markup
Author-email: Georgi Valkov <georgi.t.valkov@gmail.com>
License: BSD 3-Clause License
Project-URL: Homepage, https://github.com/gvalkov/python-ansimarkup
Classifier: Development Status :: 5 - Production/Stable
Classifier: Intended Audience :: Developers
Classifier: Topic :: Software Development :: Libraries
Classifier: Programming Language :: Python :: 3
Classifier: License :: OSI Approved :: BSD License
Classifier: Operating System :: OS Independent
Requires-Python: >=3.6
Provides-Extra: test
Provides-Extra: benchmark
License-File: LICENSE.txt
